lead/__init__.py
lead-0.0.1.dist-info/LICENSE
lead-0.0.1.dist-info/METADATA
lead-0.0.1.dist-info/WHEEL
lead-0.0.1.dist-info/top_level.txt
lead-0.0.1.dist-info/RECORD
